pytwojs/__init__.py
pytwojs/_program.py
pytwojs/exceptions.py
pytwojs/interpreter.py
pytwojs/utils.py
pytwojs-1.0.0.dist-info/METADATA
pytwojs-1.0.0.dist-info/WHEEL
pytwojs-1.0.0.dist-info/top_level.txt
pytwojs-1.0.0.dist-info/RECORD
