Metadata-Version: 2.4
Name: pytwojs
Version: 1.0.0
Summary: A high-performance Python library that relies on nodejs to execute JavaScript
Author: Samwe
Author-email: 1281722462@qq.com
Requires-Python: >=3.8.0
Dynamic: author
Dynamic: author-email
Dynamic: requires-python
Dynamic: summary
